README.md
microftp.py
setup.py
microftp.egg-info/PKG-INFO
microftp.egg-info/SOURCES.txt
microftp.egg-info/dependency_links.txt
microftp.egg-info/top_level.txt
scripts/microftpcmd