Metadata-Version: 2.1
Name: microftp
Version: 0.6.0
Summary: Small FTP library client to handle broken servers
Home-page: https://github.com/kost/microftp-python
Author: Vlatko Kosturjak
Author-email: vlatko.kosturjak@gmail.com
License: UNKNOWN
Platform: UNKNOWN
Classifier: Programming Language :: Python :: 2
Classifier: Programming Language :: Python :: 3
Classifier: License :: OSI Approved :: MIT License
Classifier: Operating System :: OS Independent
